{
  "article_slug": "2026-06/11-viridians-veligrotug-nears-a-june-30-fda-decision-for-thyroid-eye-disease-pitching-a-five-infusion-course-against-tepezza",
  "date": "2026-06-11T10:25:00.000Z",
  "corrections": [
    {
      "text": "Provenance note: the automated pipeline could not archive content snapshots for three of the four cited sources. The two PMC pages (the THRIVE primary paper, PMC12545473, and the teprotumumab review, PMC7334856) returned a reCAPTCHA browser-check interstitial instead of article text, and the THRIVE-2 abstract at academic.oup.com returned HTTP 403 to the archiver. All three sources were verified by the Chief Editor against their live URLs, and every clinical figure and direct quote in the article matched the sources verbatim. No factual claim is in dispute; this note documents only the archival limitation.",
      "severity": "clarification"
    }
  ]
}
