{
  "article_slug": "2026-06/27-nvidia-launches-halos-for-robotics-porting-its-autonomous-vehicle-safety-stack-to-humanoid-and-industrial-robots",
  "date": "2026-06-27T07:45:00.000Z",
  "corrections": [
    {
      "text": "The article's summary and Overview state that NVIDIA introduced Halos for Robotics at \"the Automate 2026 trade show in Chicago.\" None of the article's four cited sources establish the announcement venue; the NVIDIA newsroom release gives only the announcement date of June 22, 2026. The Automate 2026 venue is not supported by the cited sources.",
      "severity": "correction"
    }
  ]
}
