{
  "article_slug": "2026-05/21-biome-v2-ships-type-aware-javascript-linting-without-the-typescript-compiler",
  "date": "2026-05-21T08:39:31.000Z",
  "corrections": [
    {
      "text": "The article states that 'Reddit commenters quoted in the article describing the migration path as poor despite the flat config concept being sound in principle.' The cited InfoQ source (infoq.com/news/2026/04/eslint-10-release/) shows that the Reddit comments quoted were about switching to Biome due to ESLint's performance overhead — not about migration friction. The InfoQ article itself describes the official migration tool as making the transition 'straightforward'.",
      "severity": "correction"
    },
    {
      "text": "The article presents '~95% rule coverage' as InfoQ's characterization of Biome. The figure actually comes from a Reddit commenter quoted by InfoQ ('probably around 95%, which is enough to outweigh the performance hog eslint is'), not from InfoQ's own editorial assessment.",
      "severity": "clarification"
    }
  ]
}
