{
  "article_slug": "2026-05/24-eu-charges-meta-under-digital-services-act-for-failing-to-block-under-13-users-from-instagram-and-facebook",
  "date": "2026-05-24T17:46:26.989Z",
  "corrections": [
    {
      "text": "Two sources cited in this article — linkdash.eu and thepaypers.com — were not on the editorial source allowlist at the time of publication. Both are credible secondary publishers and all claims attributed to them are independently confirmed by the European Commission's official press release and by Euronews and The Next Web coverage. The sources have been flagged for allowlist review.",
      "severity": "clarification"
    }
  ]
}
